.travis.yml
AUTHORS
ChangeLog
LICENSE
README.rst
requirements.txt
setup.cfg
setup.py
test-requirements.txt
tox.ini
doc/Makefile
doc/make.bat
doc/source/conf.py
doc/source/index.rst
doc/source/pictool.rst
pictool/__init__.py
pictool.egg-info/PKG-INFO
pictool.egg-info/SOURCES.txt
pictool.egg-info/dependency_links.txt
pictool.egg-info/entry_points.txt
pictool.egg-info/not-zip-safe
pictool.egg-info/pbr.json
pictool.egg-info/requires.txt
pictool.egg-info/top_level.txt