Metadata-Version: 1.1
Name: pictool
Version: 0.0.1
Summary: Random collection of useful things you can do with images
Home-page: https://github.com/toabctl/pictool
Author: Thomas Bechtold
Author-email: thomasbechtold@jpberlin.de
License: UNKNOWN
Platform: UNKNOWN
Classifier: Development Status :: 4 - Beta
Classifier: Environment :: Console
Classifier: License :: OSI Approved :: GNU General Public License v3 (GPLv3)
Classifier: Programming Language :: Python
Classifier: Topic :: Utilities
